{"-N7eMFOI-35X3aOS68BO":{"date":"2022/7/23","n":"聖號","number":"1000","photoURL":"https://lh3.googleusercontent.com/a-/AFdZucpr7m8mF1mH8zAgGQv79UY-v8ZDIDQByNzoXpdf5A=s96-c","time":1658568115887,"uid":"Iqd0hkEP63MUFD4KjrU3QOIpZP13"},"-N7eRSwi0AzdxFLhfcmJ":{"date":"2022/7/23","n":"願一","number":"6800","photoURL":"https://lh3.googleusercontent.com/a-/AFdZucpr7m8mF1mH8zAgGQv79UY-v8ZDIDQByNzoXpdf5A=s96-c","time":1658569482119,"uid":"Iqd0hkEP63MUFD4KjrU3QOIpZP13"},"-N7eW8WBWXMNOZ8hHysY":{"date":"2022/7/23","n":"量子華嚴慈悲法華佛陀佛光白淨念佛寺 中華台灣國際深心靈研究教育學會 白淨白淨法白淨識","number":"10000","photoURL":"https://lh3.googleusercontent.com/a-/AFdZucoGm9HtDABDhC3JwYATTCph9qfch59kRCxV2jqriQ=s96-c","time":1658570709130,"uid":"lbOQhLBEbwQ4kmU1N0zMFeOy95r2"},"-N7ebZM9u4tl-RBMpXKE":{"date":"2022/7/23","n":"廣律","number":"1000","photoURL":"https://bestian.github.io/number/img/number.jpeg","time":1658572391927,"uid":"123"},"-N7edoDOzYKRP-mOLT-u":{"date":"2022/7/23","n":"亭妤","number":"8900","photoURL":"https://bestian.github.io/number/img/number.jpeg","time":1658572981229,"uid":"123"},"-N7edrJv-Ui7nZu7r3Yx":{"date":"2022/7/23","n":"仁維","number":"1500","photoURL":"https://bestian.github.io/number/img/number.jpeg","time":1658572993937,"uid":"123"},"-N7edvMCK1dmcb1BFCB9":{"date":"2022/7/23","n":"任秋萍","number":"1500","photoURL":"https://bestian.github.io/number/img/number.jpeg","time":1658573010467,"uid":"123"},"-N7edyQ44YOqRxbQAEru":{"date":"2022/7/23","n":"郭玉美","number":"2700","photoURL":"https://bestian.github.io/number/img/number.jpeg","time":1658573023003,"uid":"123"},"-N7ee0ZgpikuqaO4QMvF":{"date":"2022/7/23","n":"如蘭","number":"3000","photoURL":"https://bestian.github.io/number/img/number.jpeg","time":1658573035906,"uid":"123"},"-N7ee4OtAYO6MGL8HZQz":{"date":"2022/7/23","n":"陳鈴翎","number":"3000","photoURL":"https://bestian.github.io/number/img/number.jpeg","time":1658573051599,"uid":"123"},"-N7eeDkbXx0pci_DZguz":{"date":"2022/7/23","n":"周每","number":"8000","photoURL":"https://bestian.github.io/number/img/number.jpeg","time":1658573089917,"uid":"123"},"-N7eeGK-u8iL2dtqgoVM":{"date":"2022/7/23","n":"淨無","number":"20000","photoURL":"https://bestian.github.io/number/img/number.jpeg","time":1658573100438,"uid":"123"},"-N7enqFZASLpzI8kOVzg":{"date":"2022/7/23","n":"富宜","number":"2000","photoURL":"https://bestian.github.io/number/img/number.jpeg","time":1658575610966,"uid":"123"},"-N7enx91BQ4FowbmDWv1":{"date":"2022/7/23","n":"淨珠","number":"24500","photoURL":"https://bestian.github.io/number/img/number.jpeg","time":1658575639261,"uid":"123"},"-N7eo3AUjdS8lF0sZab-":{"date":"2022/7/23","n":"淨白","number":"15000","photoURL":"https://bestian.github.io/number/img/number.jpeg","time":1658575668244,"uid":"123"},"-N7eoHjDJ7KdIaHNYy9_":{"date":"2022/7/23","n":"孫奇女","number":"3000","photoURL":"https://bestian.github.io/number/img/number.jpeg","time":1658575727563,"uid":"123"},"-N7eoN6r50Q_ynrJDRot":{"date":"2022/7/23","n":"沛汝","number":"7800","photoURL":"https://bestian.github.io/number/img/number.jpeg","time":1658575749616,"uid":"123"},"-N7eoUK2-3Ghm8kgKwNB":{"date":"2022/7/23","n":"月嬌","number":"2000","photoURL":"https://bestian.github.io/number/img/number.jpeg","time":1658575779131,"uid":"123"},"-N7fH7iD5Dz8hysW5mM8":{"date":"2022/7/23","n":"聖願","number":"40000","photoURL":"https://bestian.github.io/number/img/number.jpeg","time":1658583549420,"uid":"123"},"-N7fUMp8_65r-gh1w1SD":{"date":"2022/7/23","n":"馨瑩","number":"10000","photoURL":"https://bestian.github.io/number/img/number.jpeg","time":1658587019601,"uid":"123"},"-N7fUTZKdKWwnvwv61R8":{"date":"2022/7/23","n":"沛緣","number":"3000","photoURL":"https://bestian.github.io/number/img/number.jpeg","time":1658587047209,"uid":"123"},"-N7hzoLqGuH0wvpjKQzM":{"date":"2022/7/24","n":"廣律","number":"10000","photoURL":"https://bestian.github.io/number/img/number.jpeg","time":1658629080450,"uid":"123"},"-N7jHyEHbQeWmne-wSbY":{"date":"2022/7/24","n":"聖號","number":"1000","photoURL":"https://lh3.googleusercontent.com/a-/AFdZucpr7m8mF1mH8zAgGQv79UY-v8ZDIDQByNzoXpdf5A=s96-c","time":1658650879064,"uid":"Iqd0hkEP63MUFD4KjrU3QOIpZP13"},"-N7jSjeNYReDSUaf2cGt":{"date":"2022/7/24","n":"願一","number":"1300","photoURL":"https://bestian.github.io/number/img/number.jpeg","time":1658653702967,"uid":"123"},"-N7joT3o6m5CYzsfsFVy":{"date":"2022/7/24","n":"陳玲翎","number":"3000","photoURL":"https://bestian.github.io/number/img/number.jpeg","time":1658659660065,"uid":"123"},"-N7jorHlqwUlkvwBnrVV":{"date":"2022/7/24","n":"周每","number":"8000","photoURL":"https://bestian.github.io/number/img/number.jpeg","time":1658659763303,"uid":"123"},"-N7joxVZivpJTbugC4zH":{"date":"2022/7/24","n":"亭妤","number":"13300","photoURL":"https://bestian.github.io/number/img/number.jpeg","time":1658659788767,"uid":"123"},"-N7jp-540bYBeTQbL8k6":{"date":"2022/7/24","n":"仁維","number":"1500","photoURL":"https://bestian.github.io/number/img/number.jpeg","time":1658659799361,"uid":"123"},"-N7jp3S4ezz8oVGSjMjo":{"date":"2022/7/24","n":"孫奇女","number":"3000","photoURL":"https://bestian.github.io/number/img/number.jpeg","time":1658659817217,"uid":"123"},"-N7jp7TH45DcMxQ-N9C_":{"date":"2022/7/24","n":"郭玉美","number":"2700","photoURL":"https://bestian.github.io/number/img/number.jpeg","time":1658659833678,"uid":"123"},"-N7jp9k6V3Q34jKU4HIa":{"date":"2022/7/24","n":"如蘭","number":"3000","photoURL":"https://bestian.github.io/number/img/number.jpeg","time":1658659843011,"uid":"123"},"-N7ngvLb_SB5BnhqC0fV":{"date":"2022/7/25","n":"聖號","number":"6000","photoURL":"https://bestian.github.io/number/img/number.jpeg","time":1658724791792,"uid":"123"},"-N7oyQkMY1bvsLEzY_zN":{"date":"2022/7/24","n":"沛緣","number":"3000","photoURL":"https://bestian.github.io/number/img/number.jpeg","time":1658746157840,"uid":"123"},"-N7oycJznfemzBHCEQIv":{"date":"2022/7/24","n":"馨瑩","number":"13000","photoURL":"https://bestian.github.io/number/img/number.jpeg","time":1658746209328,"uid":"123"},"-N7s3w4-BikUqmCpsHnC":{"date":"2022/7/25","n":"淨無","number":"20000","photoURL":"https://bestian.github.io/number/img/number.jpeg","time":1658798194588,"uid":"123"},"-N7s45VOiXNYIsQ6c8tq":{"date":"2022/7/25","n":"陳鈴翎","number":"3000","photoURL":"https://bestian.github.io/number/img/number.jpeg","time":1658798237308,"uid":"123"},"-N7s49BehgyCmaQOvyNP":{"date":"2022/7/25","n":"羽霈","number":"2600","photoURL":"https://bestian.github.io/number/img/number.jpeg","time":1658798252429,"uid":"123"},"-N7s4E0tnJgO8vduKbTk":{"date":"2022/7/25","n":"孫奇女","number":"3000","photoURL":"https://bestian.github.io/number/img/number.jpeg","time":1658798272221,"uid":"123"},"-N7s4I9Wo7sL38YBXjiZ":{"date":"2022/7/25","n":"周每","number":"5000","photoURL":"https://bestian.github.io/number/img/number.jpeg","time":1658798289157,"uid":"123"},"-N7s4LLV0u1rP8DMlCHg":{"date":"2022/7/25","n":"亭妤","number":"14500","photoURL":"https://bestian.github.io/number/img/number.jpeg","time":1658798302212,"uid":"123"},"-N7s4O8WEJFe24_PgJ2_":{"date":"2022/7/25","n":"仁維","number":"1500","photoURL":"https://bestian.github.io/number/img/number.jpeg","time":1658798313669,"uid":"123"},"-N7s4RA7JDks9aKFMQA1":{"date":"2022/7/25","n":"馨瑩","number":"11000","photoURL":"https://bestian.github.io/number/img/number.jpeg","time":1658798326059,"uid":"123"},"-N7s4TuVYaQh0KO0nSy_":{"date":"2022/7/25","n":"沛緣","number":"3000","photoURL":"https://bestian.github.io/number/img/number.jpeg","time":1658798337284,"uid":"123"},"-N7s4WjUmpg5i5h8M6_s":{"date":"2022/7/25","n":"富宜","number":"2000","photoURL":"https://bestian.github.io/number/img/number.jpeg","time":1658798348867,"uid":"123"},"-N7s4ZRsnRsk2K5FTMFy":{"date":"2022/7/25","n":"郭玉美","number":"2800","photoURL":"https://bestian.github.io/number/img/number.jpeg","time":1658798359964,"uid":"123"},"-N7s4b0UEDNU1IZJuWun":{"date":"2022/7/25","n":"如蘭","number":"3000","photoURL":"https://bestian.github.io/number/img/number.jpeg","time":1658798370499,"uid":"123"},"-N7s4gBkoC33EPZOXnVj":{"date":"2022/7/25","n":"淨珠","number":"25000","photoURL":"https://bestian.github.io/number/img/number.jpeg","time":1658798391700,"uid":"123"},"-N7s4iIWQFR9_42Mq5bK":{"date":"2022/7/25","n":"月嬌","number":"6000","photoURL":"https://bestian.github.io/number/img/number.jpeg","time":1658798400325,"uid":"123"},"-N7s4lQ-AKUc25rJtpUT":{"date":"2022/7/25","n":"陳芬芳","number":"400","photoURL":"https://bestian.github.io/number/img/number.jpeg","time":1658798413092,"uid":"123"},"-N7s4oJVFfGaYS_klfU_":{"date":"2022/7/25","n":"雅婕","number":"1300","photoURL":"https://bestian.github.io/number/img/number.jpeg","time":1658798424964,"uid":"123"},"-N7s4t78ciGyJXoA-Sf5":{"date":"2022/7/25","n":"淨白","number":"22000","photoURL":"https://bestian.github.io/number/img/number.jpeg","time":1658798444653,"uid":"123"},"-N7s4w4VC-425juuWT3h":{"date":"2022/7/25","n":"沛汝","number":"4500","photoURL":"https://bestian.github.io/number/img/number.jpeg","time":1658798456772,"uid":"123"},"-N7s4zHOavXaXvUeVMxt":{"date":"2022/7/25","n":"淨茜","number":"1000","photoURL":"https://bestian.github.io/number/img/number.jpeg","time":1658798469884,"uid":"123"},"-N7sVAbusf3uNKKpM6hx":{"date":"2022/7/26","n":"聖號","number":"2000","photoURL":"https://lh3.googleusercontent.com/a-/AFdZucpr7m8mF1mH8zAgGQv79UY-v8ZDIDQByNzoXpdf5A=s96-c","time":1658805336235,"uid":"Iqd0hkEP63MUFD4KjrU3QOIpZP13"},"-N7saZoJNuChTmKZaVid":{"date":"2022/7/26","n":"廣律","number":"10000","photoURL":"https://bestian.github.io/number/img/number.jpeg","time":1658807012545,"uid":"123"},"-N7seukc7ZIAGfYHxs3T":{"date":"2022/7/26","n":"許茹茜/淨茜","number":"2000","photoURL":"https://bestian.github.io/number/img/number.jpeg","time":1658808150052,"uid":"123"},"-N7sg-zmoA0iEzktiyL5":{"date":"2022/7/26","n":"林秋蓮/淨蓮","number":"2000","photoURL":"https://bestian.github.io/number/img/number.jpeg","time":1658808438022,"uid":"123"},"-N7su3vKg7Zozjan278U":{"date":"2022/7/26","n":"陳明輝／淨輝","number":"3000","photoURL":"https://bestian.github.io/number/img/number.jpeg","time":1658812123757,"uid":"123"},"-N7t5F2avBIeLZZL3w5g":{"date":"2022/7/26","n":"小雲朵","number":"2000","photoURL":"https://bestian.github.io/number/img/number.jpeg","time":1658815315744,"uid":"123"},"-N7tvVZ8fiAuM42ylpdz":{"date":"2022/7/26","n":"郭玉美","number":"2700","photoURL":"https://bestian.github.io/number/img/number.jpeg","time":1658829276301,"uid":"123"},"-N7tvfBNFa1Y6GN9Gbvs":{"date":"2022/7/26","n":"洪淑美（淨無）","number":"20000","photoURL":"https://bestian.github.io/number/img/number.jpeg","time":1658829321076,"uid":"123"},"-N7txfB8T_56V4A_M2-W":{"date":"2022/7/26","n":"賴秀珠","number":"24200","photoURL":"https://bestian.github.io/number/img/number.jpeg","time":1658829845352,"uid":"123"},"-N7txm9WyXc9c_CTn9Qu":{"date":"2022/7/26","n":"陳鈴翎","number":"3000","photoURL":"https://bestian.github.io/number/img/number.jpeg","time":1658829873637,"uid":"123"},"-N7tytHpxEeJG5a-XEOm":{"date":"2022/7/26","n":"亭妤","number":"7400","photoURL":"https://bestian.github.io/number/img/number.jpeg","time":1658830164413,"uid":"123"},"-N7tz9LPv7WcOOOgUZky":{"date":"2022/7/26","n":"仁維","number":"1500","photoURL":"https://bestian.github.io/number/img/number.jpeg","time":1658830234290,"uid":"123"},"-N7tzNMgR3NRbW67gEnj":{"date":"2022/7/26","n":"周每","number":"8000","photoURL":"https://bestian.github.io/number/img/number.jpeg","time":1658830291814,"uid":"123"},"-N7u043-a5P58n9QjkKR":{"date":"2022/7/26","n":"孫奇女","number":"3000","photoURL":"https://bestian.github.io/number/img/number.jpeg","time":1658830737781,"uid":"123"},"-N7u0ALtTYFZBK5L5UDc":{"date":"2022/7/26","n":"李羽霈","number":"3300","photoURL":"https://bestian.github.io/number/img/number.jpeg","time":1658830763554,"uid":"123"},"-N7u3S9HnPMxyzBjUFMw":{"date":"2022/7/26","n":"月嬌","number":"3600","photoURL":"https://bestian.github.io/number/img/number.jpeg","time":1658831622910,"uid":"123"},"-N7u49m1Ihce1yikMi3v":{"date":"2022/7/26","n":"陳如蘭","number":"3000","photoURL":"https://bestian.github.io/number/img/number.jpeg","time":1658831808333,"uid":"123"},"-N7u6Rf22Rglp9ZQGLAp":{"date":"2022/7/26","n":"陳芬芳","number":"1000","photoURL":"https://bestian.github.io/number/img/number.jpeg","time":1658832406286,"uid":"123"},"-N7u6qg09MaPAoMoLqz0":{"date":"2022/7/26","n":"張蓮禮 淨白","number":"21000","photoURL":"https://bestian.github.io/number/img/number.jpeg","time":1658832513913,"uid":"123"},"-N7u8sPeZHshjxMFh7BK":{"date":"2022/7/26","n":"廣弘","number":"10000","photoURL":"https://bestian.github.io/number/img/number.jpeg","time":1658833045261,"uid":"123"},"-N7u9A40z2HhajHEIX05":{"date":"2022/7/26","n":"林俊德","number":"20100","photoURL":"https://bestian.github.io/number/img/number.jpeg","time":1658833121696,"uid":"123"},"-N7u9rsw_Iun1LNYW5lI":{"date":"2022/7/26","n":"江沛汝","number":"12960","photoURL":"https://bestian.github.io/number/img/number.jpeg","time":1658833305238,"uid":"123"},"-N7uAFRbo0jHwbEFd1AE":{"date":"2022/7/26","n":"任秋萍","number":"1200","photoURL":"https://bestian.github.io/number/img/number.jpeg","time":1658833405253,"uid":"123"},"-N7uAprb5dNIk7EfEVBT":{"date":"2022/7/26","n":"鄧雅婕","number":"3000","photoURL":"https://bestian.github.io/number/img/number.jpeg","time":1658833558743,"uid":"123"},"-N7uF-0q_fF45_sL3Knd":{"date":"2022/7/26","n":"馨瑩","number":"10000","photoURL":"https://bestian.github.io/number/img/number.jpeg","time":1658834649112,"uid":"123"},"-N7uF4PULXadFGbNKwxA":{"date":"2022/7/26","n":"沛緣","number":"2200","photoURL":"https://bestian.github.io/number/img/number.jpeg","time":1658834671229,"uid":"123"},"-N7uGasAFrvYy3-xdpaH":{"date":"2022/7/26","n":"陳碧球","number":"7500","photoURL":"https://bestian.github.io/number/img/number.jpeg","time":1658835069747,"uid":"123"},"-N7uKxdRwmm-XXRWkqXW":{"date":"2022/7/26","n":"富宜","number":"2000","photoURL":"https://bestian.github.io/number/img/number.jpeg","time":1658836152375,"uid":"123"},"-N7uMwbI_abkH280FHIN":{"date":"2022/7/26","n":"聖願","number":"15000","photoURL":"https://bestian.github.io/number/img/number.jpeg","time":1658836731776,"uid":"123"},"-N7x-d0S79-PARfUkpIh":{"date":"2022/7/27","n":"謝美雲","number":"2500","photoURL":"https://bestian.github.io/number/img/number.jpeg","time":1658880953000,"uid":"123"},"-N7yN6UEv8gjw94gb_JX":{"date":"2022/7/27","n":"聖號","number":"1000","photoURL":"https://bestian.github.io/number/img/number.jpeg","time":1658903885241,"uid":"123"},"-N7yPp47Ur99yrBp5LRr":{"date":"2022/7/26","n":"傳年","number":"1221","photoURL":"https://bestian.github.io/number/img/number.jpeg","time":1658904596907,"uid":"123"},"-N7yPuDJRaq578L0aPWn":{"date":"2022/7/27","n":"傳年","number":"1025","photoURL":"https://bestian.github.io/number/img/number.jpeg","time":1658904617979,"uid":"123"}}